app/__init__.py
app/routes.py
app/wsgi.py
cttdepeace-0.1.data/scripts/cttdepeace
cttdepeace-0.1.dist-info/METADATA
cttdepeace-0.1.dist-info/WHEEL
cttdepeace-0.1.dist-info/top_level.txt
cttdepeace-0.1.dist-info/RECORD
